[{
	"id": 1,
	"pergunta": "Quando você usa o banheiro para <br/> fazer o número 1 ou 2, o que você<br/> <bold>DEVE</bold> fazer?",
	"respostas": [{
		"isRight": false,
		"content": "Compartilhar sua obra<br/> com seu colega",
		"id":1
	}, {
		"isRight": false,
		"content": "Colocar o veú na noiva",
		"id":2
	}, {
		"isRight": false,
		"content": "Não lavar as Mãos",
		"id":3
	}, {
		"isRight": true,
		"content": "Dar a descarga e lavar as mãos",
		"id":4
	}]
},{
	"id": 2,
	"pergunta": "Quando você traz um pão fresco e esquece de trazer algo para passar. o que você <bold>não</bold> deve fazer:",
	"respostas": [{
		"isRight": false,
		"content": "comer pão puro",
		"id":1
	}, {
		"isRight": false,
		"content": "ligar para o suco & mania",
		"id":2
	}, {
		"isRight": false,
		"content": "usar margarina de alguém",
		"id":3
	}, {
		"isRight": true,
		"content": "pedir emprestado",
		"id":4
	}]
}]